simple503/__init__.py
simple503/__main__.py
simple503/config.py
simple503/py.typed
simple503-0.4.0.dist-info/LICENSE
simple503-0.4.0.dist-info/METADATA
simple503-0.4.0.dist-info/WHEEL
simple503-0.4.0.dist-info/entry_points.txt
simple503-0.4.0.dist-info/RECORD
