Metadata-Version: 2.1
Name: simple503
Version: 0.4.0
Summary: PEP 503 Python package repository generator.
Author-email: Dominic Davis-Foster <dominic@davis-foster.co.uk>
License: MIT
Keywords: pep503,pep658,pip,pypi
Home-page: https://github.com/repo-helper/simple503
Project-URL: Issue Tracker, https://github.com/repo-helper/simple503/issues
Project-URL: Source Code, https://github.com/repo-helper/simple503
Project-URL: Documentation, https://simple503.readthedocs.io/en/latest
Platform: Windows
Platform: macOS
Platform: Linux
Classifier: Development Status :: 3 - Alpha
Classifier: Environment :: Console
Classifier: Intended Audience :: Developers
Classifier: License :: OSI Approved :: MIT License
Classifier: Operating System :: OS Independent
Classifier: Programming Language :: Python
Classifier: Programming Language :: Python :: 3 :: Only
Classifier: Programming Language :: Python :: 3.6
Classifier: Programming Language :: Python :: 3.7
Classifier: Programming Language :: Python :: 3.8
Classifier: Programming Language :: Python :: 3.9
Classifier: Programming Language :: Python :: 3.10
Classifier: Programming Language :: Python :: 3.11
Classifier: Programming Language :: Python :: Implementation :: CPython
Classifier: Programming Language :: Python :: Implementation :: PyPy
Classifier: Topic :: System :: Archiving :: Packaging
Classifier: Typing :: Typed
Requires-Python: >=3.6
Requires-Dist: airium>=0.2.2
Requires-Dist: apeye>=1.0.1
Requires-Dist: click>=8.0.1
Requires-Dist: consolekit>=1.2.2
Requires-Dist: dataclasses>=0.8; python_version == "3.6"
Requires-Dist: dist-meta>=0.1.0
Requires-Dist: dom-toml>=0.5.1
Requires-Dist: domdf-python-tools>=2.9.1
Requires-Dist: natsort>=7.1.1
Requires-Dist: shippinglabel>=0.15.0
Requires-Dist: typing-extensions>=3.7.4.1
Requires-Dist: beautifulsoup4>=4.9.3; extra == 'incremental'
Requires-Dist: beautifulsoup4>=4.9.3; extra == 'all'
Provides-Extra: incremental
Provides-Extra: all
